{
  "students": {
    "marvin": {
      "name": "Marvin",
      "level": "B2",
      "variant": "European",
      "addedAt": "2026-02-04",
      "targetLevel": null,
      "notes": "",
      "strengths": [],
      "weaknesses": [],
      "goals": []
    },
    "christian": {
      "name": "Christian",
      "level": "B1",
      "variant": "Brazilian",
      "addedAt": "2026-02-04",
      "targetLevel": null,
      "notes": "",
      "strengths": [],
      "weaknesses": [],
      "goals": []
    },
    "amanda": {
      "name": "Amanda",
      "level": "B2",
      "variant": "Brazilian",
      "addedAt": "2026-02-04",
      "targetLevel": null,
      "notes": "",
      "strengths": [],
      "weaknesses": [],
      "goals": []
    }
  },
  "sessions": {
    "marvin": [
      {
        "date": "2026-02-03",
        "topic": "Família de palavras (Word Families)",
        "material": "Textbook p.204, exercise 15-6",
        "skills": ["word derivation", "noun-adjective-adverb-verb conversion", "morphology"],
        "notes": "No issues"
      }
    ],
    "christian": [
      {
        "date": "2026-02-04",
        "topic": "Pretérito Perfeito (Simple Past)",
        "material": "printables/preterite-worksheet-christian.html",
        "skills": ["preterite conjugation", "regular verbs", "irregular verbs"],
        "notes": "Completed 70-exercise worksheet"
      }
    ],
    "amanda": []
  },
  "metadata": {
    "createdAt": "2026-02-04",
    "lastUpdated": "2026-02-04",
    "version": "1.0"
  }
}
